{"headers":["tableName","columnName","ordinalPosition","dataType"],"tables":["Comments","Accounts","Transactions","Blocks","Followers","Reblogs","TxEscrowApproves","TxEscrowDisputes","TxEscrowReleases","TxEscrowTransfers","TxFeeds","TxLimitOrders","TxPows","TxTransfers","TxVotes","TxWithdraws","TxWithdrawVestingRoutes","TxWitnessUpdates","TxAccountCreates","TxDeclineVotingRights","TxDelegateVestingShares","TxDeleteComments","TxAccountRecovers","TxAccountUpdates","TxAccountWitnessProxies","TxAccountWitnessVotes","TxClaimRewardBalances","TxComments","TxCommentsOptions","TxConverts","TxCustoms","VOAuthorRewards","VOCommentBenefactorRewards","VOCurationRewards","VOFillConvertRequests","VOFillOrders","VOFillTransferFromSavings","VOFillVestingWithdraws","VOInterests","VOLiquidityRewards","VOProducerRewards","VOReturnVestingDelegations","VOShutdownWitnesses"],"rows":[{"tableName":"Reblogs","columnName":"account","ordinalPosition":1,"dataType":"varchar"},{"tableName":"Reblogs","columnName":"author","ordinalPosition":2,"dataType":"varchar"},{"tableName":"Reblogs","columnName":"permlink","ordinalPosition":3,"dataType":"varchar"},{"tableName":"Reblogs","columnName":"timestamp","ordinalPosition":4,"dataType":"datetime"},{"tableName":"TxEscrowApproves","columnName":"ID","ordinalPosition":1,"dataType":"int"},{"tableName":"TxEscrowApproves","columnName":"tx_id","ordinalPosition":2,"dataType":"int"},{"tableName":"TxEscrowApproves","columnName":"from","ordinalPosition":3,"dataType":"varchar"},{"tableName":"TxEscrowApproves","columnName":"to","ordinalPosition":4,"dataType":"varchar"},{"tableName":"TxEscrowApproves","columnName":"agent","ordinalPosition":5,"dataType":"varchar"},{"tableName":"TxEscrowApproves","columnName":"who","ordinalPosition":6,"dataType":"varchar"},{"tableName":"TxEscrowApproves","columnName":"escrow_id","ordinalPosition":7,"dataType":"bigint"},{"tableName":"TxEscrowApproves","columnName":"approve","ordinalPosition":8,"dataType":"bit"},{"tableName":"TxEscrowApproves","columnName":"timestamp","ordinalPosition":9,"dataType":"datetime"},{"tableName":"TxEscrowDisputes","columnName":"ID","ordinalPosition":1,"dataType":"int"},{"tableName":"TxEscrowDisputes","columnName":"tx_id","ordinalPosition":2,"dataType":"int"},{"tableName":"TxEscrowDisputes","columnName":"from","ordinalPosition":3,"dataType":"varchar"},{"tableName":"TxEscrowDisputes","columnName":"to","ordinalPosition":4,"dataType":"varchar"},{"tableName":"TxEscrowDisputes","columnName":"agent","ordinalPosition":5,"dataType":"varchar"},{"tableName":"TxEscrowDisputes","columnName":"who","ordinalPosition":6,"dataType":"varchar"},{"tableName":"TxEscrowDisputes","columnName":"escrow_id","ordinalPosition":7,"dataType":"bigint"},{"tableName":"TxEscrowDisputes","columnName":"timestamp","ordinalPosition":8,"dataType":"datetime"},{"tableName":"TxEscrowReleases","columnName":"ID","ordinalPosition":1,"dataType":"int"},{"tableName":"TxEscrowReleases","columnName":"tx_id","ordinalPosition":2,"dataType":"int"},{"tableName":"TxEscrowReleases","columnName":"from","ordinalPosition":3,"dataType":"varchar"},{"tableName":"TxEscrowReleases","columnName":"to","ordinalPosition":4,"dataType":"varchar"},{"tableName":"TxEscrowReleases","columnName":"agent","ordinalPosition":5,"dataType":"varchar"},{"tableName":"TxEscrowReleases","columnName":"who","ordinalPosition":6,"dataType":"varchar"},{"tableName":"TxEscrowReleases","columnName":"receiver","ordinalPosition":7,"dataType":"varchar"},{"tableName":"TxEscrowReleases","columnName":"escrow_id","ordinalPosition":8,"dataType":"bigint"},{"tableName":"TxEscrowReleases","columnName":"sdb_amount","ordinalPosition":9,"dataType":"money"},{"tableName":"TxEscrowReleases","columnName":"steem_amount","ordinalPosition":10,"dataType":"money"},{"tableName":"TxEscrowReleases","columnName":"timestamp","ordinalPosition":11,"dataType":"datetime"},{"tableName":"TxEscrowTransfers","columnName":"ID","ordinalPosition":1,"dataType":"int"},{"tableName":"TxEscrowTransfers","columnName":"tx_id","ordinalPosition":2,"dataType":"int"},{"tableName":"TxEscrowTransfers","columnName":"from","ordinalPosition":3,"dataType":"varchar"},{"tableName":"TxEscrowTransfers","columnName":"to","ordinalPosition":4,"dataType":"varchar"},{"tableName":"TxEscrowTransfers","columnName":"sdb_amount","ordinalPosition":5,"dataType":"money"},{"tableName":"TxEscrowTransfers","columnName":"steem_amount","ordinalPosition":6,"dataType":"money"},{"tableName":"TxEscrowTransfers","columnName":"escrow_id","ordinalPosition":7,"dataType":"bigint"},{"tableName":"TxEscrowTransfers","columnName":"agent","ordinalPosition":8,"dataType":"varchar"},{"tableName":"TxEscrowTransfers","columnName":"fee","ordinalPosition":9,"dataType":"money"},{"tableName":"TxEscrowTransfers","columnName":"fee_symbol","ordinalPosition":10,"dataType":"varchar"},{"tableName":"TxEscrowTransfers","columnName":"json_meta","ordinalPosition":11,"dataType":"varchar"},{"tableName":"TxEscrowTransfers","columnName":"ratification_deadline","ordinalPosition":12,"dataType":"datetime"},{"tableName":"TxEscrowTransfers","columnName":"escrow_expiration","ordinalPosition":13,"dataType":"datetime"},{"tableName":"TxEscrowTransfers","columnName":"timestamp","ordinalPosition":14,"dataType":"datetime"},{"tableName":"TxFeeds","columnName":"ID","ordinalPosition":1,"dataType":"int"},{"tableName":"TxFeeds","columnName":"tx_id","ordinalPosition":2,"dataType":"int"},{"tableName":"TxFeeds","columnName":"publisher","ordinalPosition":3,"dataType":"varchar"},{"tableName":"TxFeeds","columnName":"exchange_rate_base","ordinalPosition":4,"dataType":"money"},{"tableName":"TxFeeds","columnName":"exchange_rate_quote","ordinalPosition":5,"dataType":"money"},{"tableName":"TxFeeds","columnName":"timestamp","ordinalPosition":6,"dataType":"datetime"},{"tableName":"TxLimitOrders","columnName":"ID","ordinalPosition":1,"dataType":"int"},{"tableName":"TxLimitOrders","columnName":"tx_id","ordinalPosition":2,"dataType":"int"},{"tableName":"TxLimitOrders","columnName":"owner","ordinalPosition":3,"dataType":"varchar"},{"tableName":"TxLimitOrders","columnName":"orderid","ordinalPosition":4,"dataType":"bigint"},{"tableName":"TxLimitOrders","columnName":"cancel","ordinalPosition":5,"dataType":"bit"},{"tableName":"TxLimitOrders","columnName":"amount_to_sell","ordinalPosition":6,"dataType":"money"},{"tableName":"TxLimitOrders","columnName":"min_to_receive","ordinalPosition":7,"dataType":"money"},{"tableName":"TxLimitOrders","columnName":"exchange_rate_base","ordinalPosition":8,"dataType":"money"},{"tableName":"TxLimitOrders","columnName":"exchange_rate_quote","ordinalPosition":9,"dataType":"money"},{"tableName":"TxLimitOrders","columnName":"fill_or_kill","ordinalPosition":10,"dataType":"bit"},{"tableName":"TxLimitOrders","columnName":"expiration","ordinalPosition":11,"dataType":"datetime"},{"tableName":"TxLimitOrders","columnName":"timestamp","ordinalPosition":12,"dataType":"datetime"},{"tableName":"TxPows","columnName":"ID","ordinalPosition":1,"dataType":"int"},{"tableName":"TxPows","columnName":"tx_id","ordinalPosition":2,"dataType":"int"},{"tableName":"TxPows","columnName":"worker_account","ordinalPosition":3,"dataType":"varchar"},{"tableName":"TxPows","columnName":"block_id","ordinalPosition":4,"dataType":"varchar"},{"tableName":"TxPows","columnName":"timestamp","ordinalPosition":5,"dataType":"datetime"},{"tableName":"TxTransfers","columnName":"ID","ordinalPosition":1,"dataType":"int"},{"tableName":"TxTransfers","columnName":"tx_id","ordinalPosition":2,"dataType":"int"},{"tableName":"TxTransfers","columnName":"type","ordinalPosition":3,"dataType":"varchar"},{"tableName":"TxTransfers","columnName":"from","ordinalPosition":4,"dataType":"varchar"},{"tableName":"TxTransfers","columnName":"to","ordinalPosition":5,"dataType":"varchar"},{"tableName":"TxTransfers","columnName":"amount","ordinalPosition":6,"dataType":"money"},{"tableName":"TxTransfers","columnName":"amount_symbol","ordinalPosition":7,"dataType":"varchar"},{"tableName":"TxTransfers","columnName":"memo","ordinalPosition":8,"dataType":"nvarchar"},{"tableName":"TxTransfers","columnName":"request_id","ordinalPosition":9,"dataType":"bigint"},{"tableName":"TxTransfers","columnName":"timestamp","ordinalPosition":10,"dataType":"datetime"},{"tableName":"TxVotes","columnName":"ID","ordinalPosition":1,"dataType":"int"},{"tableName":"TxVotes","columnName":"tx_id","ordinalPosition":2,"dataType":"int"},{"tableName":"TxVotes","columnName":"voter","ordinalPosition":3,"dataType":"varchar"},{"tableName":"TxVotes","columnName":"author","ordinalPosition":4,"dataType":"varchar"},{"tableName":"TxVotes","columnName":"permlink","ordinalPosition":5,"dataType":"varchar"},{"tableName":"TxVotes","columnName":"weight","ordinalPosition":6,"dataType":"int"},{"tableName":"TxVotes","columnName":"timestamp","ordinalPosition":7,"dataType":"datetime"},{"tableName":"TxWithdraws","columnName":"ID","ordinalPosition":1,"dataType":"int"},{"tableName":"TxWithdraws","columnName":"tx_id","ordinalPosition":2,"dataType":"int"},{"tableName":"TxWithdraws","columnName":"account","ordinalPosition":3,"dataType":"varchar"},{"tableName":"TxWithdraws","columnName":"vesting_shares","ordinalPosition":4,"dataType":"money"},{"tableName":"TxWithdraws","columnName":"timestamp","ordinalPosition":5,"dataType":"datetime"},{"tableName":"TxWithdrawVestingRoutes","columnName":"ID","ordinalPosition":1,"dataType":"int"},{"tableName":"TxWithdrawVestingRoutes","columnName":"tx_id","ordinalPosition":2,"dataType":"int"},{"tableName":"TxWithdrawVestingRoutes","columnName":"from_account","ordinalPosition":3,"dataType":"varchar"},{"tableName":"TxWithdrawVestingRoutes","columnName":"to_account","ordinalPosition":4,"dataType":"varchar"},{"tableName":"TxWithdrawVestingRoutes","columnName":"percent","ordinalPosition":5,"dataType":"smallint"},{"tableName":"TxWithdrawVestingRoutes","columnName":"auto_vest","ordinalPosition":6,"dataType":"bit"},{"tableName":"TxWithdrawVestingRoutes","columnName":"timestamp","ordinalPosition":7,"dataType":"datetime"},{"tableName":"TxWitnessUpdates","columnName":"ID","ordinalPosition":1,"dataType":"int"},{"tableName":"TxWitnessUpdates","columnName":"tx_id","ordinalPosition":2,"dataType":"int"},{"tableName":"TxWitnessUpdates","columnName":"owner","ordinalPosition":3,"dataType":"varchar"},{"tableName":"TxWitnessUpdates","columnName":"url","ordinalPosition":4,"dataType":"varchar"},{"tableName":"TxWitnessUpdates","columnName":"block_signing_key","ordinalPosition":5,"dataType":"varchar"},{"tableName":"TxWitnessUpdates","columnName":"props_account_creation_fee","ordinalPosition":6,"dataType":"money"},{"tableName":"TxWitnessUpdates","columnName":"props_maximum_block_size","ordinalPosition":7,"dataType":"int"},{"tableName":"TxWitnessUpdates","columnName":"props_sbd_interest_rate","ordinalPosition":8,"dataType":"int"},{"tableName":"TxWitnessUpdates","columnName":"fee","ordinalPosition":9,"dataType":"money"},{"tableName":"TxWitnessUpdates","columnName":"timestamp","ordinalPosition":10,"dataType":"datetime"},{"tableName":"TxAccountCreates","columnName":"ID","ordinalPosition":1,"dataType":"int"},{"tableName":"TxAccountCreates","columnName":"tx_id","ordinalPosition":2,"dataType":"int"},{"tableName":"TxAccountCreates","columnName":"fee","ordinalPosition":3,"dataType":"money"},{"tableName":"TxAccountCreates","columnName":"delegation","ordinalPosition":4,"dataType":"money"},{"tableName":"TxAccountCreates","columnName":"creator","ordinalPosition":5,"dataType":"varchar"},{"tableName":"TxAccountCreates","columnName":"new_account_name","ordinalPosition":6,"dataType":"varchar"},{"tableName":"TxAccountCreates","columnName":"owner_key","ordinalPosition":7,"dataType":"varchar"},{"tableName":"TxAccountCreates","columnName":"active_key","ordinalPosition":8,"dataType":"varchar"},{"tableName":"TxAccountCreates","columnName":"posting_key","ordinalPosition":9,"dataType":"varchar"},{"tableName":"TxAccountCreates","columnName":"memo_key","ordinalPosition":10,"dataType":"varchar"},{"tableName":"TxAccountCreates","columnName":"json_metadata","ordinalPosition":11,"dataType":"varchar"},{"tableName":"TxAccountCreates","columnName":"timestamp","ordinalPosition":12,"dataType":"datetime"},{"tableName":"Comments","columnName":"ID","ordinalPosition":1,"dataType":"int"},{"tableName":"Comments","columnName":"author","ordinalPosition":2,"dataType":"varchar"},{"tableName":"Comments","columnName":"permlink","ordinalPosition":3,"dataType":"varchar"},{"tableName":"Comments","columnName":"category","ordinalPosition":4,"dataType":"varchar"},{"tableName":"Comments","columnName":"parent_author","ordinalPosition":5,"dataType":"varchar"},{"tableName":"Comments","columnName":"parent_permlink","ordinalPosition":6,"dataType":"varchar"},{"tableName":"Comments","columnName":"title","ordinalPosition":7,"dataType":"nvarchar"},{"tableName":"Comments","columnName":"body","ordinalPosition":8,"dataType":"nvarchar"},{"tableName":"Comments","columnName":"json_metadata","ordinalPosition":9,"dataType":"nvarchar"},{"tableName":"Comments","columnName":"last_update","ordinalPosition":10,"dataType":"datetime"},{"tableName":"Comments","columnName":"created","ordinalPosition":11,"dataType":"datetime"},{"tableName":"Comments","columnName":"active","ordinalPosition":12,"dataType":"datetime"},{"tableName":"Comments","columnName":"last_payout","ordinalPosition":13,"dataType":"datetime"},{"tableName":"Comments","columnName":"depth","ordinalPosition":14,"dataType":"int"},{"tableName":"Comments","columnName":"children","ordinalPosition":15,"dataType":"int"},{"tableName":"Comments","columnName":"net_rshares","ordinalPosition":16,"dataType":"bigint"},{"tableName":"Comments","columnName":"abs_rshares","ordinalPosition":17,"dataType":"bigint"},{"tableName":"Comments","columnName":"vote_rshares","ordinalPosition":18,"dataType":"bigint"},{"tableName":"Comments","columnName":"children_abs_rshares","ordinalPosition":19,"dataType":"bigint"},{"tableName":"Comments","columnName":"cashout_time","ordinalPosition":20,"dataType":"datetime"},{"tableName":"Comments","columnName":"max_cashout_time","ordinalPosition":21,"dataType":"datetime"},{"tableName":"Comments","columnName":"total_vote_weight","ordinalPosition":22,"dataType":"float"},{"tableName":"Comments","columnName":"reward_weight","ordinalPosition":23,"dataType":"int"},{"tableName":"Comments","columnName":"total_payout_value","ordinalPosition":24,"dataType":"money"},{"tableName":"Comments","columnName":"curator_payout_value","ordinalPosition":25,"dataType":"money"},{"tableName":"Comments","columnName":"author_rewards","ordinalPosition":26,"dataType":"money"},{"tableName":"Comments","columnName":"net_votes","ordinalPosition":27,"dataType":"int"},{"tableName":"Comments","columnName":"root_comment","ordinalPosition":28,"dataType":"varchar"},{"tableName":"Comments","columnName":"mode","ordinalPosition":29,"dataType":"varchar"},{"tableName":"Comments","columnName":"max_accepted_payout","ordinalPosition":30,"dataType":"money"},{"tableName":"Comments","columnName":"percent_steem_dollars","ordinalPosition":31,"dataType":"int"},{"tableName":"Comments","columnName":"allow_replies","ordinalPosition":32,"dataType":"bit"},{"tableName":"Comments","columnName":"allow_votes","ordinalPosition":33,"dataType":"bit"},{"tableName":"Comments","columnName":"allow_curation_rewards","ordinalPosition":34,"dataType":"bit"},{"tableName":"Comments","columnName":"beneficiaries","ordinalPosition":35,"dataType":"varchar"},{"tableName":"Comments","columnName":"url","ordinalPosition":36,"dataType":"varchar"},{"tableName":"Comments","columnName":"root_title","ordinalPosition":37,"dataType":"nvarchar"},{"tableName":"Comments","columnName":"pending_payout_value","ordinalPosition":38,"dataType":"money"},{"tableName":"Comments","columnName":"total_pending_payout_value","ordinalPosition":39,"dataType":"money"},{"tableName":"Comments","columnName":"active_votes","ordinalPosition":40,"dataType":"varchar"},{"tableName":"Comments","columnName":"replies","ordinalPosition":41,"dataType":"varchar"},{"tableName":"Comments","columnName":"author_reputation","ordinalPosition":42,"dataType":"bigint"},{"tableName":"Comments","columnName":"promoted","ordinalPosition":43,"dataType":"varchar"},{"tableName":"Comments","columnName":"body_length","ordinalPosition":44,"dataType":"int"},{"tableName":"Comments","columnName":"reblogged_by","ordinalPosition":45,"dataType":"varchar"},{"tableName":"Comments","columnName":"body_language","ordinalPosition":46,"dataType":"varchar"},{"tableName":"Comments","columnName":"dirty","ordinalPosition":47,"dataType":"bit"},{"tableName":"Comments","columnName":"TS","ordinalPosition":48,"dataType":"timestamp"},{"tableName":"VOAuthorRewards","columnName":"ID","ordinalPosition":1,"dataType":"int"},{"tableName":"VOAuthorRewards","columnName":"block_num","ordinalPosition":2,"dataType":"int"},{"tableName":"VOAuthorRewards","columnName":"timestamp","ordinalPosition":3,"dataType":"datetime"},{"tableName":"VOAuthorRewards","columnName":"author","ordinalPosition":4,"dataType":"varchar"},{"tableName":"VOAuthorRewards","columnName":"permlink","ordinalPosition":5,"dataType":"varchar"},{"tableName":"VOAuthorRewards","columnName":"sdb_payout","ordinalPosition":6,"dataType":"money"},{"tableName":"VOAuthorRewards","columnName":"steem_payout","ordinalPosition":7,"dataType":"money"},{"tableName":"VOAuthorRewards","columnName":"vesting_payout","ordinalPosition":8,"dataType":"money"},{"tableName":"VOCommentBenefactorRewards","columnName":"ID","ordinalPosition":1,"dataType":"int"},{"tableName":"VOCommentBenefactorRewards","columnName":"block_num","ordinalPosition":2,"dataType":"int"},{"tableName":"VOCommentBenefactorRewards","columnName":"timestamp","ordinalPosition":3,"dataType":"datetime"},{"tableName":"VOCommentBenefactorRewards","columnName":"benefactor","ordinalPosition":4,"dataType":"varchar"},{"tableName":"VOCommentBenefactorRewards","columnName":"author","ordinalPosition":5,"dataType":"varchar"},{"tableName":"VOCommentBenefactorRewards","columnName":"permlink","ordinalPosition":6,"dataType":"varchar"},{"tableName":"VOCommentBenefactorRewards","columnName":"reward","ordinalPosition":7,"dataType":"varchar"},{"tableName":"VOCurationRewards","columnName":"ID","ordinalPosition":1,"dataType":"int"},{"tableName":"VOCurationRewards","columnName":"block_num","ordinalPosition":2,"dataType":"int"},{"tableName":"VOCurationRewards","columnName":"timestamp","ordinalPosition":3,"dataType":"datetime"},{"tableName":"VOCurationRewards","columnName":"curator","ordinalPosition":4,"dataType":"varchar"},{"tableName":"VOCurationRewards","columnName":"author","ordinalPosition":5,"dataType":"varchar"},{"tableName":"VOCurationRewards","columnName":"permlink","ordinalPosition":6,"dataType":"varchar"},{"tableName":"VOCurationRewards","columnName":"reward","ordinalPosition":7,"dataType":"varchar"},{"tableName":"VOFillConvertRequests","columnName":"ID","ordinalPosition":1,"dataType":"int"},{"tableName":"VOFillConvertRequests","columnName":"block_num","ordinalPosition":2,"dataType":"int"},{"tableName":"VOFillConvertRequests","columnName":"timestamp","ordinalPosition":3,"dataType":"datetime"},{"tableName":"VOFillConvertRequests","columnName":"owner","ordinalPosition":4,"dataType":"varchar"},{"tableName":"VOFillConvertRequests","columnName":"requestid","ordinalPosition":5,"dataType":"bigint"},{"tableName":"VOFillConvertRequests","columnName":"amount_in","ordinalPosition":6,"dataType":"varchar"},{"tableName":"VOFillConvertRequests","columnName":"amount_out","ordinalPosition":7,"dataType":"varchar"},{"tableName":"VOFillOrders","columnName":"ID","ordinalPosition":1,"dataType":"int"},{"tableName":"VOFillOrders","columnName":"block_num","ordinalPosition":2,"dataType":"int"},{"tableName":"VOFillOrders","columnName":"timestamp","ordinalPosition":3,"dataType":"datetime"},{"tableName":"VOFillOrders","columnName":"current_owner","ordinalPosition":4,"dataType":"varchar"},{"tableName":"VOFillOrders","columnName":"current_orderid","ordinalPosition":5,"dataType":"bigint"},{"tableName":"VOFillOrders","columnName":"current_pays","ordinalPosition":6,"dataType":"varchar"},{"tableName":"VOFillOrders","columnName":"open_owner","ordinalPosition":7,"dataType":"varchar"},{"tableName":"VOFillOrders","columnName":"open_orderid","ordinalPosition":8,"dataType":"bigint"},{"tableName":"VOFillOrders","columnName":"open_pays","ordinalPosition":9,"dataType":"varchar"},{"tableName":"VOFillTransferFromSavings","columnName":"ID","ordinalPosition":1,"dataType":"int"},{"tableName":"VOFillTransferFromSavings","columnName":"block_num","ordinalPosition":2,"dataType":"int"},{"tableName":"VOFillTransferFromSavings","columnName":"timestamp","ordinalPosition":3,"dataType":"datetime"},{"tableName":"VOFillTransferFromSavings","columnName":"from","ordinalPosition":4,"dataType":"varchar"},{"tableName":"VOFillTransferFromSavings","columnName":"to","ordinalPosition":5,"dataType":"varchar"},{"tableName":"VOFillTransferFromSavings","columnName":"amount","ordinalPosition":6,"dataType":"money"},{"tableName":"VOFillTransferFromSavings","columnName":"amount_symbol","ordinalPosition":7,"dataType":"varchar"},{"tableName":"VOFillTransferFromSavings","columnName":"requestid","ordinalPosition":8,"dataType":"bigint"},{"tableName":"VOFillTransferFromSavings","columnName":"memo","ordinalPosition":9,"dataType":"nvarchar"},{"tableName":"VOFillVestingWithdraws","columnName":"ID","ordinalPosition":1,"dataType":"int"},{"tableName":"VOFillVestingWithdraws","columnName":"block_num","ordinalPosition":2,"dataType":"int"},{"tableName":"VOFillVestingWithdraws","columnName":"timestamp","ordinalPosition":3,"dataType":"datetime"},{"tableName":"VOFillVestingWithdraws","columnName":"from_account","ordinalPosition":4,"dataType":"varchar"},{"tableName":"VOFillVestingWithdraws","columnName":"to_account","ordinalPosition":5,"dataType":"varchar"},{"tableName":"VOFillVestingWithdraws","columnName":"withdrawn","ordinalPosition":6,"dataType":"varchar"},{"tableName":"VOFillVestingWithdraws","columnName":"deposited","ordinalPosition":7,"dataType":"varchar"},{"tableName":"VOInterests","columnName":"ID","ordinalPosition":1,"dataType":"int"},{"tableName":"VOInterests","columnName":"block_num","ordinalPosition":2,"dataType":"int"},{"tableName":"VOInterests","columnName":"timestamp","ordinalPosition":3,"dataType":"datetime"},{"tableName":"VOInterests","columnName":"owner","ordinalPosition":4,"dataType":"varchar"},{"tableName":"VOInterests","columnName":"Interest","ordinalPosition":5,"dataType":"money"},{"tableName":"VOLiquidityRewards","columnName":"ID","ordinalPosition":1,"dataType":"int"},{"tableName":"VOLiquidityRewards","columnName":"block_num","ordinalPosition":2,"dataType":"int"},{"tableName":"VOLiquidityRewards","columnName":"timestamp","ordinalPosition":3,"dataType":"datetime"},{"tableName":"VOLiquidityRewards","columnName":"owner","ordinalPosition":4,"dataType":"varchar"},{"tableName":"VOLiquidityRewards","columnName":"payout","ordinalPosition":5,"dataType":"varchar"},{"tableName":"VOProducerRewards","columnName":"ID","ordinalPosition":1,"dataType":"int"},{"tableName":"VOProducerRewards","columnName":"block_num","ordinalPosition":2,"dataType":"int"},{"tableName":"VOProducerRewards","columnName":"timestamp","ordinalPosition":3,"dataType":"datetime"},{"tableName":"VOProducerRewards","columnName":"producer","ordinalPosition":4,"dataType":"varchar"},{"tableName":"VOProducerRewards","columnName":"vesting_shares","ordinalPosition":5,"dataType":"money"},{"tableName":"VOReturnVestingDelegations","columnName":"ID","ordinalPosition":1,"dataType":"int"},{"tableName":"VOReturnVestingDelegations","columnName":"block_num","ordinalPosition":2,"dataType":"int"},{"tableName":"VOReturnVestingDelegations","columnName":"timestamp","ordinalPosition":3,"dataType":"datetime"},{"tableName":"VOReturnVestingDelegations","columnName":"account","ordinalPosition":4,"dataType":"varchar"},{"tableName":"VOReturnVestingDelegations","columnName":"amount","ordinalPosition":5,"dataType":"money"},{"tableName":"VOReturnVestingDelegations","columnName":"amount_symbol","ordinalPosition":6,"dataType":"varchar"},{"tableName":"VOShutdownWitnesses","columnName":"ID","ordinalPosition":1,"dataType":"int"},{"tableName":"VOShutdownWitnesses","columnName":"block_num","ordinalPosition":2,"dataType":"int"},{"tableName":"VOShutdownWitnesses","columnName":"timestamp","ordinalPosition":3,"dataType":"datetime"},{"tableName":"VOShutdownWitnesses","columnName":"owner","ordinalPosition":4,"dataType":"varchar"},{"tableName":"Transactions","columnName":"tx_id","ordinalPosition":1,"dataType":"int"},{"tableName":"Transactions","columnName":"block_num","ordinalPosition":2,"dataType":"int"},{"tableName":"Transactions","columnName":"transaction_num","ordinalPosition":3,"dataType":"tinyint"},{"tableName":"Transactions","columnName":"ref_block_num","ordinalPosition":4,"dataType":"int"},{"tableName":"Transactions","columnName":"ref_block_prefix","ordinalPosition":5,"dataType":"bigint"},{"tableName":"Transactions","columnName":"expiration","ordinalPosition":6,"dataType":"datetime"},{"tableName":"Transactions","columnName":"type","ordinalPosition":7,"dataType":"varchar"},{"tableName":"Blocks","columnName":"block_num","ordinalPosition":1,"dataType":"int"},{"tableName":"Blocks","columnName":"previous","ordinalPosition":2,"dataType":"varchar"},{"tableName":"Blocks","columnName":"timestamp","ordinalPosition":3,"dataType":"datetime"},{"tableName":"Blocks","columnName":"witness","ordinalPosition":4,"dataType":"varchar"},{"tableName":"Blocks","columnName":"witness_signature","ordinalPosition":5,"dataType":"varchar"},{"tableName":"Blocks","columnName":"transaction_merkle_root","ordinalPosition":6,"dataType":"varchar"},{"tableName":"Accounts","columnName":"id","ordinalPosition":1,"dataType":"varchar"},{"tableName":"Accounts","columnName":"name","ordinalPosition":2,"dataType":"varchar"},{"tableName":"Accounts","columnName":"owner","ordinalPosition":3,"dataType":"varchar"},{"tableName":"Accounts","columnName":"active","ordinalPosition":4,"dataType":"varchar"},{"tableName":"Accounts","columnName":"posting","ordinalPosition":5,"dataType":"varchar"},{"tableName":"Accounts","columnName":"memo_key","ordinalPosition":6,"dataType":"varchar"},{"tableName":"Accounts","columnName":"json_metadata","ordinalPosition":7,"dataType":"nvarchar"},{"tableName":"Accounts","columnName":"proxy","ordinalPosition":8,"dataType":"varchar"},{"tableName":"Accounts","columnName":"last_owner_update","ordinalPosition":9,"dataType":"datetime"},{"tableName":"Accounts","columnName":"last_account_update","ordinalPosition":10,"dataType":"datetime"},{"tableName":"Accounts","columnName":"created","ordinalPosition":11,"dataType":"datetime"},{"tableName":"Accounts","columnName":"mined","ordinalPosition":12,"dataType":"bit"},{"tableName":"Accounts","columnName":"owner_challenged","ordinalPosition":13,"dataType":"bit"},{"tableName":"Accounts","columnName":"active_challenged","ordinalPosition":14,"dataType":"bit"},{"tableName":"Accounts","columnName":"recovery_account","ordinalPosition":15,"dataType":"varchar"},{"tableName":"Accounts","columnName":"last_account_recovery","ordinalPosition":16,"dataType":"datetime"},{"tableName":"Accounts","columnName":"reset_account","ordinalPosition":17,"dataType":"varchar"},{"tableName":"Accounts","columnName":"comment_count","ordinalPosition":18,"dataType":"bigint"},{"tableName":"Accounts","columnName":"lifetime_vote_count","ordinalPosition":19,"dataType":"bigint"},{"tableName":"Accounts","columnName":"post_count","ordinalPosition":20,"dataType":"bigint"},{"tableName":"Accounts","columnName":"can_vote","ordinalPosition":21,"dataType":"bit"},{"tableName":"Accounts","columnName":"voting_power","ordinalPosition":22,"dataType":"smallint"},{"tableName":"Accounts","columnName":"last_vote_time","ordinalPosition":23,"dataType":"datetime"},{"tableName":"Accounts","columnName":"balance","ordinalPosition":24,"dataType":"varchar"},{"tableName":"Accounts","columnName":"savings_balance","ordinalPosition":25,"dataType":"varchar"},{"tableName":"Accounts","columnName":"sbd_balance","ordinalPosition":26,"dataType":"varchar"},{"tableName":"Accounts","columnName":"sbd_seconds","ordinalPosition":27,"dataType":"bigint"},{"tableName":"Accounts","columnName":"sbd_seconds_last_update","ordinalPosition":28,"dataType":"datetime"},{"tableName":"Accounts","columnName":"sbd_last_interest_payment","ordinalPosition":29,"dataType":"datetime"},{"tableName":"Accounts","columnName":"savings_sbd_balance","ordinalPosition":30,"dataType":"varchar"},{"tableName":"Accounts","columnName":"savings_sbd_seconds","ordinalPosition":31,"dataType":"bigint"},{"tableName":"Accounts","columnName":"savings_sbd_seconds_last_update","ordinalPosition":32,"dataType":"datetime"},{"tableName":"Accounts","columnName":"savings_sbd_last_interest_payment","ordinalPosition":33,"dataType":"datetime"},{"tableName":"Accounts","columnName":"savings_withdraw_requests","ordinalPosition":34,"dataType":"int"},{"tableName":"Accounts","columnName":"vesting_shares","ordinalPosition":35,"dataType":"varchar"},{"tableName":"Accounts","columnName":"delegated_vesting_shares","ordinalPosition":36,"dataType":"varchar"},{"tableName":"Accounts","columnName":"received_vesting_shares","ordinalPosition":37,"dataType":"varchar"},{"tableName":"Accounts","columnName":"vesting_withdraw_rate","ordinalPosition":38,"dataType":"varchar"},{"tableName":"Accounts","columnName":"next_vesting_withdrawal","ordinalPosition":39,"dataType":"datetime"},{"tableName":"Accounts","columnName":"withdrawn","ordinalPosition":40,"dataType":"bigint"},{"tableName":"Accounts","columnName":"to_withdraw","ordinalPosition":41,"dataType":"bigint"},{"tableName":"Accounts","columnName":"withdraw_routes","ordinalPosition":42,"dataType":"smallint"},{"tableName":"Accounts","columnName":"curation_rewards","ordinalPosition":43,"dataType":"bigint"},{"tableName":"Accounts","columnName":"posting_rewards","ordinalPosition":44,"dataType":"bigint"},{"tableName":"Accounts","columnName":"proxied_vsf_votes","ordinalPosition":45,"dataType":"varchar"},{"tableName":"Accounts","columnName":"witnesses_voted_for","ordinalPosition":46,"dataType":"smallint"},{"tableName":"Accounts","columnName":"average_bandwidth","ordinalPosition":47,"dataType":"bigint"},{"tableName":"Accounts","columnName":"lifetime_bandwidth","ordinalPosition":48,"dataType":"bigint"},{"tableName":"Accounts","columnName":"last_bandwidth_update","ordinalPosition":49,"dataType":"datetime"},{"tableName":"Accounts","columnName":"average_market_bandwidth","ordinalPosition":50,"dataType":"bigint"},{"tableName":"Accounts","columnName":"last_market_bandwidth_update","ordinalPosition":51,"dataType":"datetime"},{"tableName":"Accounts","columnName":"last_post","ordinalPosition":52,"dataType":"datetime"},{"tableName":"Accounts","columnName":"last_root_post","ordinalPosition":53,"dataType":"datetime"},{"tableName":"Accounts","columnName":"vesting_balance","ordinalPosition":54,"dataType":"varchar"},{"tableName":"Accounts","columnName":"reputation","ordinalPosition":55,"dataType":"bigint"},{"tableName":"Accounts","columnName":"transfer_history","ordinalPosition":56,"dataType":"varchar"},{"tableName":"Accounts","columnName":"market_history","ordinalPosition":57,"dataType":"varchar"},{"tableName":"Accounts","columnName":"post_history","ordinalPosition":58,"dataType":"varchar"},{"tableName":"Accounts","columnName":"vote_history","ordinalPosition":59,"dataType":"varchar"},{"tableName":"Accounts","columnName":"other_history","ordinalPosition":60,"dataType":"varchar"},{"tableName":"Accounts","columnName":"witness_votes","ordinalPosition":61,"dataType":"varchar"},{"tableName":"Accounts","columnName":"dirty","ordinalPosition":62,"dataType":"bit"},{"tableName":"Accounts","columnName":"TS","ordinalPosition":63,"dataType":"timestamp"},{"tableName":"TxDeclineVotingRights","columnName":"ID","ordinalPosition":1,"dataType":"int"},{"tableName":"TxDeclineVotingRights","columnName":"tx_id","ordinalPosition":2,"dataType":"int"},{"tableName":"TxDeclineVotingRights","columnName":"account","ordinalPosition":3,"dataType":"varchar"},{"tableName":"TxDeclineVotingRights","columnName":"decline","ordinalPosition":4,"dataType":"bit"},{"tableName":"TxDeclineVotingRights","columnName":"timestamp","ordinalPosition":5,"dataType":"datetime"},{"tableName":"TxDelegateVestingShares","columnName":"ID","ordinalPosition":1,"dataType":"int"},{"tableName":"TxDelegateVestingShares","columnName":"tx_id","ordinalPosition":2,"dataType":"int"},{"tableName":"TxDelegateVestingShares","columnName":"delegator","ordinalPosition":3,"dataType":"varchar"},{"tableName":"TxDelegateVestingShares","columnName":"delegatee","ordinalPosition":4,"dataType":"varchar"},{"tableName":"TxDelegateVestingShares","columnName":"vesting_shares","ordinalPosition":5,"dataType":"money"},{"tableName":"TxDelegateVestingShares","columnName":"timestamp","ordinalPosition":6,"dataType":"datetime"},{"tableName":"TxDeleteComments","columnName":"ID","ordinalPosition":1,"dataType":"int"},{"tableName":"TxDeleteComments","columnName":"tx_id","ordinalPosition":2,"dataType":"int"},{"tableName":"TxDeleteComments","columnName":"author","ordinalPosition":3,"dataType":"varchar"},{"tableName":"TxDeleteComments","columnName":"permlink","ordinalPosition":4,"dataType":"varchar"},{"tableName":"TxDeleteComments","columnName":"timestamp","ordinalPosition":5,"dataType":"datetime"},{"tableName":"TxAccountRecovers","columnName":"ID","ordinalPosition":1,"dataType":"int"},{"tableName":"TxAccountRecovers","columnName":"tx_id","ordinalPosition":2,"dataType":"int"},{"tableName":"TxAccountRecovers","columnName":"recovery_account","ordinalPosition":3,"dataType":"varchar"},{"tableName":"TxAccountRecovers","columnName":"account_to_recover","ordinalPosition":4,"dataType":"varchar"},{"tableName":"TxAccountRecovers","columnName":"recovered","ordinalPosition":5,"dataType":"bit"},{"tableName":"TxAccountRecovers","columnName":"timestamp","ordinalPosition":6,"dataType":"datetime"},{"tableName":"TxAccountUpdates","columnName":"ID","ordinalPosition":1,"dataType":"int"},{"tableName":"TxAccountUpdates","columnName":"tx_id","ordinalPosition":2,"dataType":"int"},{"tableName":"TxAccountUpdates","columnName":"account","ordinalPosition":3,"dataType":"varchar"},{"tableName":"TxAccountUpdates","columnName":"key_auth1","ordinalPosition":4,"dataType":"varchar"},{"tableName":"TxAccountUpdates","columnName":"key_auth2","ordinalPosition":5,"dataType":"varchar"},{"tableName":"TxAccountUpdates","columnName":"memo_key","ordinalPosition":6,"dataType":"varchar"},{"tableName":"TxAccountUpdates","columnName":"json_metadata","ordinalPosition":7,"dataType":"varchar"},{"tableName":"TxAccountUpdates","columnName":"timestamp","ordinalPosition":8,"dataType":"datetime"},{"tableName":"TxAccountWitnessProxies","columnName":"ID","ordinalPosition":1,"dataType":"int"},{"tableName":"TxAccountWitnessProxies","columnName":"tx_id","ordinalPosition":2,"dataType":"int"},{"tableName":"TxAccountWitnessProxies","columnName":"account","ordinalPosition":3,"dataType":"varchar"},{"tableName":"TxAccountWitnessProxies","columnName":"Proxy","ordinalPosition":4,"dataType":"varchar"},{"tableName":"TxAccountWitnessProxies","columnName":"timestamp","ordinalPosition":5,"dataType":"datetime"},{"tableName":"TxAccountWitnessVotes","columnName":"ID","ordinalPosition":1,"dataType":"int"},{"tableName":"TxAccountWitnessVotes","columnName":"tx_id","ordinalPosition":2,"dataType":"int"},{"tableName":"TxAccountWitnessVotes","columnName":"account","ordinalPosition":3,"dataType":"varchar"},{"tableName":"TxAccountWitnessVotes","columnName":"witness","ordinalPosition":4,"dataType":"varchar"},{"tableName":"TxAccountWitnessVotes","columnName":"approve","ordinalPosition":5,"dataType":"bit"},{"tableName":"TxAccountWitnessVotes","columnName":"timestamp","ordinalPosition":6,"dataType":"datetime"},{"tableName":"TxClaimRewardBalances","columnName":"ID","ordinalPosition":1,"dataType":"int"},{"tableName":"TxClaimRewardBalances","columnName":"tx_id","ordinalPosition":2,"dataType":"int"},{"tableName":"TxClaimRewardBalances","columnName":"account","ordinalPosition":3,"dataType":"varchar"},{"tableName":"TxClaimRewardBalances","columnName":"reward_steem","ordinalPosition":4,"dataType":"money"},{"tableName":"TxClaimRewardBalances","columnName":"reward_sbd","ordinalPosition":5,"dataType":"money"},{"tableName":"TxClaimRewardBalances","columnName":"reward_vests","ordinalPosition":6,"dataType":"money"},{"tableName":"TxClaimRewardBalances","columnName":"timestamp","ordinalPosition":7,"dataType":"datetime"},{"tableName":"TxComments","columnName":"ID","ordinalPosition":1,"dataType":"int"},{"tableName":"TxComments","columnName":"tx_id","ordinalPosition":2,"dataType":"int"},{"tableName":"TxComments","columnName":"author","ordinalPosition":3,"dataType":"varchar"},{"tableName":"TxComments","columnName":"permlink","ordinalPosition":4,"dataType":"varchar"},{"tableName":"TxComments","columnName":"parent_author","ordinalPosition":5,"dataType":"varchar"},{"tableName":"TxComments","columnName":"parent_permlink","ordinalPosition":6,"dataType":"varchar"},{"tableName":"TxComments","columnName":"title","ordinalPosition":7,"dataType":"nvarchar"},{"tableName":"TxComments","columnName":"body","ordinalPosition":8,"dataType":"nvarchar"},{"tableName":"TxComments","columnName":"json_metadata","ordinalPosition":9,"dataType":"varchar"},{"tableName":"TxComments","columnName":"timestamp","ordinalPosition":10,"dataType":"datetime"},{"tableName":"Followers","columnName":"follower","ordinalPosition":1,"dataType":"varchar"},{"tableName":"Followers","columnName":"following","ordinalPosition":2,"dataType":"varchar"},{"tableName":"TxCommentsOptions","columnName":"ID","ordinalPosition":1,"dataType":"int"},{"tableName":"TxCommentsOptions","columnName":"tx_id","ordinalPosition":2,"dataType":"int"},{"tableName":"TxCommentsOptions","columnName":"author","ordinalPosition":3,"dataType":"varchar"},{"tableName":"TxCommentsOptions","columnName":"permlink","ordinalPosition":4,"dataType":"varchar"},{"tableName":"TxCommentsOptions","columnName":"max_accepted_payout","ordinalPosition":5,"dataType":"money"},{"tableName":"TxCommentsOptions","columnName":"percent_steem_dollars","ordinalPosition":6,"dataType":"smallint"},{"tableName":"TxCommentsOptions","columnName":"allow_votes","ordinalPosition":7,"dataType":"bit"},{"tableName":"TxCommentsOptions","columnName":"allow_curation_rewards","ordinalPosition":8,"dataType":"bit"},{"tableName":"TxCommentsOptions","columnName":"timestamp","ordinalPosition":9,"dataType":"datetime"},{"tableName":"TxConverts","columnName":"ID","ordinalPosition":1,"dataType":"int"},{"tableName":"TxConverts","columnName":"tx_id","ordinalPosition":2,"dataType":"int"},{"tableName":"TxConverts","columnName":"owner","ordinalPosition":3,"dataType":"varchar"},{"tableName":"TxConverts","columnName":"requestid","ordinalPosition":4,"dataType":"bigint"},{"tableName":"TxConverts","columnName":"amount","ordinalPosition":5,"dataType":"money"},{"tableName":"TxConverts","columnName":"timestamp","ordinalPosition":6,"dataType":"datetime"},{"tableName":"TxCustoms","columnName":"ID","ordinalPosition":1,"dataType":"int"},{"tableName":"TxCustoms","columnName":"tx_id","ordinalPosition":2,"dataType":"int"},{"tableName":"TxCustoms","columnName":"tid","ordinalPosition":3,"dataType":"varchar"},{"tableName":"TxCustoms","columnName":"json_metadata","ordinalPosition":4,"dataType":"varchar"},{"tableName":"TxCustoms","columnName":"timestamp","ordinalPosition":5,"dataType":"datetime"}]}